rest_framework_jwt/__init__.py
rest_framework_jwt/authentication.py
rest_framework_jwt/compat.py
rest_framework_jwt/models.py
rest_framework_jwt/serializers.py
rest_framework_jwt/settings.py
rest_framework_jwt/test.py
rest_framework_jwt/utils.py
rest_framework_jwt/views.py
rest_framework_jwt/locale/en_US/LC_MESSAGES/django.po
rest_framework_jwt_db_enabled/__init__.py
rest_framework_jwt_db_enabled/authentication.py
rest_framework_jwt_db_enabled/compat.py
rest_framework_jwt_db_enabled/models.py
rest_framework_jwt_db_enabled/serializers.py
rest_framework_jwt_db_enabled/settings.py
rest_framework_jwt_db_enabled/test.py
rest_framework_jwt_db_enabled/utils.py
rest_framework_jwt_db_enabled/views.py
rest_framework_jwt_db_enabled/locale/en_US/LC_MESSAGES/django.po
tests/__init__.py
tests/conftest.py
tests/models.py
tests/test_authentication.py
tests/test_serializers.py
tests/test_utils.py
tests/test_views.py
tests/urls.py
tests/utils.py
drf_jwt_db_enabled-0.0.7.dist-info/LICENSE
drf_jwt_db_enabled-0.0.7.dist-info/METADATA
drf_jwt_db_enabled-0.0.7.dist-info/WHEEL
drf_jwt_db_enabled-0.0.7.dist-info/top_level.txt
drf_jwt_db_enabled-0.0.7.dist-info/RECORD
